[
   {
      "name": "Al Kittah",
      "countryCode": "JO",
      "stateCode": "JA"
   },
   {
      "name": "Balīlā",
      "countryCode": "JO",
      "stateCode": "JA"
   },
   {
      "name": "Burmā",
      "countryCode": "JO",
      "stateCode": "JA"
   },
   {
      "name": "Jarash",
      "countryCode": "JO",
      "stateCode": "JA"
   },
   {
      "name": "Qafqafā",
      "countryCode": "JO",
      "stateCode": "JA"
   },
   {
      "name": "Raymūn",
      "countryCode": "JO",
      "stateCode": "JA"
   },
   {
      "name": "Sakib",
      "countryCode": "JO",
      "stateCode": "JA"
   },
   {
      "name": "Sūf",
      "countryCode": "JO",
      "stateCode": "JA"
   }
]