[
   {
      "name": "Buga",
      "countryCode": "NG",
      "stateCode": "NA"
   },
   {
      "name": "Doma",
      "countryCode": "NG",
      "stateCode": "NA"
   },
   {
      "name": "Keffi",
      "countryCode": "NG",
      "stateCode": "NA"
   },
   {
      "name": "Lafia",
      "countryCode": "NG",
      "stateCode": "NA"
   },
   {
      "name": "Nasarawa",
      "countryCode": "NG",
      "stateCode": "NA"
   },
   {
      "name": "Wamba",
      "countryCode": "NG",
      "stateCode": "NA"
   }
]