[
   {
      "name": "Altstätten",
      "countryCode": "CH",
      "stateCode": "SG"
   },
   {
      "name": "Amden",
      "countryCode": "CH",
      "stateCode": "SG"
   },
   {
      "name": "Andwil",
      "countryCode": "CH",
      "stateCode": "SG"
   },
   {
      "name": "Au",
      "countryCode": "CH",
      "stateCode": "SG"
   },
   {
      "name": "Bad Ragaz",
      "countryCode": "CH",
      "stateCode": "SG"
   },
   {
      "name": "Balgach",
      "countryCode": "CH",
      "stateCode": "SG"
   },
   {
      "name": "Benken",
      "countryCode": "CH",
      "stateCode": "SG"
   },
   {
      "name": "Bronschhofen",
      "countryCode": "CH",
      "stateCode": "SG"
   },
   {
      "name": "Buchs",
      "countryCode": "CH",
      "stateCode": "SG"
   },
   {
      "name": "Bütschwil",
      "countryCode": "CH",
      "stateCode": "SG"
   },
   {
      "name": "Degersheim",
      "countryCode": "CH",
      "stateCode": "SG"
   },
   {
      "name": "Diepoldsau",
      "countryCode": "CH",
      "stateCode": "SG"
   },
   {
      "name": "Ebnat-Kappel",
      "countryCode": "CH",
      "stateCode": "SG"
   },
   {
      "name": "Eggersriet",
      "countryCode": "CH",
      "stateCode": "SG"
   },
   {
      "name": "Eichberg",
      "countryCode": "CH",
      "stateCode": "SG"
   },
   {
      "name": "Eschenbach",
      "countryCode": "CH",
      "stateCode": "SG"
   },
   {
      "name": "Flawil",
      "countryCode": "CH",
      "stateCode": "SG"
   },
   {
      "name": "Flums",
      "countryCode": "CH",
      "stateCode": "SG"
   },
   {
      "name": "Gams",
      "countryCode": "CH",
      "stateCode": "SG"
   },
   {
      "name": "Ganterschwil",
      "countryCode": "CH",
      "stateCode": "SG"
   },
   {
      "name": "Goldach",
      "countryCode": "CH",
      "stateCode": "SG"
   },
   {
      "name": "Goldingen",
      "countryCode": "CH",
      "stateCode": "SG"
   },
   {
      "name": "Gommiswald",
      "countryCode": "CH",
      "stateCode": "SG"
   },
   {
      "name": "Gossau",
      "countryCode": "CH",
      "stateCode": "SG"
   },
   {
      "name": "Grabs",
      "countryCode": "CH",
      "stateCode": "SG"
   },
   {
      "name": "Haag (Rheintal)",
      "countryCode": "CH",
      "stateCode": "SG"
   },
   {
      "name": "Horn",
      "countryCode": "CH",
      "stateCode": "SG"
   },
   {
      "name": "Häggenschwil",
      "countryCode": "CH",
      "stateCode": "SG"
   },
   {
      "name": "Jona",
      "countryCode": "CH",
      "stateCode": "SG"
   },
   {
      "name": "Jonschwil",
      "countryCode": "CH",
      "stateCode": "SG"
   },
   {
      "name": "Kaltbrunn",
      "countryCode": "CH",
      "stateCode": "SG"
   },
   {
      "name": "Kirchberg",
      "countryCode": "CH",
      "stateCode": "SG"
   },
   {
      "name": "Krummenau",
      "countryCode": "CH",
      "stateCode": "SG"
   },
   {
      "name": "Lichtensteig",
      "countryCode": "CH",
      "stateCode": "SG"
   },
   {
      "name": "Lütisburg",
      "countryCode": "CH",
      "stateCode": "SG"
   },
   {
      "name": "Mogelsberg",
      "countryCode": "CH",
      "stateCode": "SG"
   },
   {
      "name": "Mosnang",
      "countryCode": "CH",
      "stateCode": "SG"
   },
   {
      "name": "Muolen",
      "countryCode": "CH",
      "stateCode": "SG"
   },
   {
      "name": "Mörschwil",
      "countryCode": "CH",
      "stateCode": "SG"
   },
   {
      "name": "Niederbüren",
      "countryCode": "CH",
      "stateCode": "SG"
   },
   {
      "name": "Niederhelfenschwil",
      "countryCode": "CH",
      "stateCode": "SG"
   },
   {
      "name": "Oberhelfenschwil",
      "countryCode": "CH",
      "stateCode": "SG"
   },
   {
      "name": "Oberriet",
      "countryCode": "CH",
      "stateCode": "SG"
   },
   {
      "name": "Oberuzwil",
      "countryCode": "CH",
      "stateCode": "SG"
   },
   {
      "name": "Quarten",
      "countryCode": "CH",
      "stateCode": "SG"
   },
   {
      "name": "Rapperswil",
      "countryCode": "CH",
      "stateCode": "SG"
   },
   {
      "name": "Rebstein",
      "countryCode": "CH",
      "stateCode": "SG"
   },
   {
      "name": "Rheineck",
      "countryCode": "CH",
      "stateCode": "SG"
   },
   {
      "name": "Rorschach",
      "countryCode": "CH",
      "stateCode": "SG"
   },
   {
      "name": "Rüthi",
      "countryCode": "CH",
      "stateCode": "SG"
   },
   {
      "name": "Sankt Gallen",
      "countryCode": "CH",
      "stateCode": "SG"
   },
   {
      "name": "Sankt Gallenkappel",
      "countryCode": "CH",
      "stateCode": "SG"
   },
   {
      "name": "Sankt Margrethen",
      "countryCode": "CH",
      "stateCode": "SG"
   },
   {
      "name": "Sankt Peterzell",
      "countryCode": "CH",
      "stateCode": "SG"
   },
   {
      "name": "Sargans",
      "countryCode": "CH",
      "stateCode": "SG"
   },
   {
      "name": "Schmerikon",
      "countryCode": "CH",
      "stateCode": "SG"
   },
   {
      "name": "Schänis",
      "countryCode": "CH",
      "stateCode": "SG"
   },
   {
      "name": "Sennwald",
      "countryCode": "CH",
      "stateCode": "SG"
   },
   {
      "name": "Sevelen",
      "countryCode": "CH",
      "stateCode": "SG"
   },
   {
      "name": "Thal",
      "countryCode": "CH",
      "stateCode": "SG"
   },
   {
      "name": "Uznach",
      "countryCode": "CH",
      "stateCode": "SG"
   },
   {
      "name": "Uzwil",
      "countryCode": "CH",
      "stateCode": "SG"
   },
   {
      "name": "Wahlkreis Rheintal",
      "countryCode": "CH",
      "stateCode": "SG"
   },
   {
      "name": "Wahlkreis Rorschach",
      "countryCode": "CH",
      "stateCode": "SG"
   },
   {
      "name": "Wahlkreis Sarganserland",
      "countryCode": "CH",
      "stateCode": "SG"
   },
   {
      "name": "Wahlkreis See-Gaster",
      "countryCode": "CH",
      "stateCode": "SG"
   },
   {
      "name": "Wahlkreis St. Gallen",
      "countryCode": "CH",
      "stateCode": "SG"
   },
   {
      "name": "Wahlkreis Toggenburg",
      "countryCode": "CH",
      "stateCode": "SG"
   },
   {
      "name": "Wahlkreis Werdenberg",
      "countryCode": "CH",
      "stateCode": "SG"
   },
   {
      "name": "Wahlkreis Wil",
      "countryCode": "CH",
      "stateCode": "SG"
   },
   {
      "name": "Waldkirch",
      "countryCode": "CH",
      "stateCode": "SG"
   },
   {
      "name": "Walenstadt",
      "countryCode": "CH",
      "stateCode": "SG"
   },
   {
      "name": "Wattwil",
      "countryCode": "CH",
      "stateCode": "SG"
   },
   {
      "name": "Weesen",
      "countryCode": "CH",
      "stateCode": "SG"
   },
   {
      "name": "Wil",
      "countryCode": "CH",
      "stateCode": "SG"
   },
   {
      "name": "Wildhaus",
      "countryCode": "CH",
      "stateCode": "SG"
   },
   {
      "name": "Wittenbach",
      "countryCode": "CH",
      "stateCode": "SG"
   },
   {
      "name": "Zuzwil",
      "countryCode": "CH",
      "stateCode": "SG"
   }
]