[
   {
      "name": "Hachimantai",
      "countryCode": "JP",
      "stateCode": "03"
   },
   {
      "name": "Hachimantai Shi",
      "countryCode": "JP",
      "stateCode": "03"
   },
   {
      "name": "Hanamaki",
      "countryCode": "JP",
      "stateCode": "03"
   },
   {
      "name": "Hanamaki Shi",
      "countryCode": "JP",
      "stateCode": "03"
   },
   {
      "name": "Ichinohe",
      "countryCode": "JP",
      "stateCode": "03"
   },
   {
      "name": "Ichinoseki",
      "countryCode": "JP",
      "stateCode": "03"
   },
   {
      "name": "Ichinoseki-shi",
      "countryCode": "JP",
      "stateCode": "03"
   },
   {
      "name": "Iwate-gun",
      "countryCode": "JP",
      "stateCode": "03"
   },
   {
      "name": "Kamaishi",
      "countryCode": "JP",
      "stateCode": "03"
   },
   {
      "name": "Kamaishi-shi",
      "countryCode": "JP",
      "stateCode": "03"
   },
   {
      "name": "Kitakami",
      "countryCode": "JP",
      "stateCode": "03"
   },
   {
      "name": "Kitakami-shi",
      "countryCode": "JP",
      "stateCode": "03"
   },
   {
      "name": "Kuji",
      "countryCode": "JP",
      "stateCode": "03"
   },
   {
      "name": "Kuji-shi",
      "countryCode": "JP",
      "stateCode": "03"
   },
   {
      "name": "Miyako",
      "countryCode": "JP",
      "stateCode": "03"
   },
   {
      "name": "Miyako-shi",
      "countryCode": "JP",
      "stateCode": "03"
   },
   {
      "name": "Mizusawa",
      "countryCode": "JP",
      "stateCode": "03"
   },
   {
      "name": "Morioka",
      "countryCode": "JP",
      "stateCode": "03"
   },
   {
      "name": "Morioka-shi",
      "countryCode": "JP",
      "stateCode": "03"
   },
   {
      "name": "Ninohe",
      "countryCode": "JP",
      "stateCode": "03"
   },
   {
      "name": "Ninohe Shi",
      "countryCode": "JP",
      "stateCode": "03"
   },
   {
      "name": "Rikuzentakata-shi",
      "countryCode": "JP",
      "stateCode": "03"
   },
   {
      "name": "Shizukuishi",
      "countryCode": "JP",
      "stateCode": "03"
   },
   {
      "name": "Takizawa-shi",
      "countryCode": "JP",
      "stateCode": "03"
   },
   {
      "name": "Tōno",
      "countryCode": "JP",
      "stateCode": "03"
   },
   {
      "name": "Tōno-shi",
      "countryCode": "JP",
      "stateCode": "03"
   },
   {
      "name": "Yamada",
      "countryCode": "JP",
      "stateCode": "03"
   },
   {
      "name": "Ōfunato",
      "countryCode": "JP",
      "stateCode": "03"
   },
   {
      "name": "Ōfunato-shi",
      "countryCode": "JP",
      "stateCode": "03"
   },
   {
      "name": "Ōshū",
      "countryCode": "JP",
      "stateCode": "03"
   },
   {
      "name": "Ōshū-shi",
      "countryCode": "JP",
      "stateCode": "03"
   },
   {
      "name": "Ōtsuchi",
      "countryCode": "JP",
      "stateCode": "03"
   }
]