[
   {
      "name": "Becsehely",
      "countryCode": "HU",
      "stateCode": "ZA",
      "latitude": "46.44755000",
      "longitude": "16.77710000"
   },
   {
      "name": "Cserszegtomaj",
      "countryCode": "HU",
      "stateCode": "ZA",
      "latitude": "46.80165000",
      "longitude": "17.22096000"
   },
   {
      "name": "Gyenesdiás",
      "countryCode": "HU",
      "stateCode": "ZA",
      "latitude": "46.77058000",
      "longitude": "17.28660000"
   },
   {
      "name": "Hévíz",
      "countryCode": "HU",
      "stateCode": "ZA",
      "latitude": "46.79031000",
      "longitude": "17.18408000"
   },
   {
      "name": "Keszthely",
      "countryCode": "HU",
      "stateCode": "ZA",
      "latitude": "46.76812000",
      "longitude": "17.24317000"
   },
   {
      "name": "Keszthelyi Járás",
      "countryCode": "HU",
      "stateCode": "ZA",
      "latitude": "46.78356000",
      "longitude": "17.22381000"
   },
   {
      "name": "Lenti",
      "countryCode": "HU",
      "stateCode": "ZA",
      "latitude": "46.62403000",
      "longitude": "16.53863000"
   },
   {
      "name": "Lenti Járás",
      "countryCode": "HU",
      "stateCode": "ZA",
      "latitude": "46.65649000",
      "longitude": "16.57443000"
   },
   {
      "name": "Letenye",
      "countryCode": "HU",
      "stateCode": "ZA",
      "latitude": "46.43301000",
      "longitude": "16.72583000"
   },
   {
      "name": "Letenyei Járás",
      "countryCode": "HU",
      "stateCode": "ZA",
      "latitude": "46.50552000",
      "longitude": "16.76503000"
   },
   {
      "name": "Murakeresztúr",
      "countryCode": "HU",
      "stateCode": "ZA",
      "latitude": "46.36422000",
      "longitude": "16.88177000"
   },
   {
      "name": "Nagykanizsa",
      "countryCode": "HU",
      "stateCode": "ZA",
      "latitude": "46.45347000",
      "longitude": "16.99104000"
   },
   {
      "name": "Nagykanizsai Járás",
      "countryCode": "HU",
      "stateCode": "ZA",
      "latitude": "46.51873000",
      "longitude": "17.04433000"
   },
   {
      "name": "Pacsa",
      "countryCode": "HU",
      "stateCode": "ZA",
      "latitude": "46.71981000",
      "longitude": "17.01401000"
   },
   {
      "name": "Sármellék",
      "countryCode": "HU",
      "stateCode": "ZA",
      "latitude": "46.71221000",
      "longitude": "17.16865000"
   },
   {
      "name": "Türje",
      "countryCode": "HU",
      "stateCode": "ZA",
      "latitude": "46.98366000",
      "longitude": "17.10742000"
   },
   {
      "name": "Vonyarcvashegy",
      "countryCode": "HU",
      "stateCode": "ZA",
      "latitude": "46.75742000",
      "longitude": "17.31172000"
   },
   {
      "name": "Zalaegerszeg",
      "countryCode": "HU",
      "stateCode": "ZA",
      "latitude": "46.84000000",
      "longitude": "16.84389000"
   },
   {
      "name": "Zalaegerszegi Járás",
      "countryCode": "HU",
      "stateCode": "ZA",
      "latitude": "46.80000000",
      "longitude": "16.83000000"
   },
   {
      "name": "Zalakomár",
      "countryCode": "HU",
      "stateCode": "ZA",
      "latitude": "46.53795000",
      "longitude": "17.18094000"
   },
   {
      "name": "Zalalövő",
      "countryCode": "HU",
      "stateCode": "ZA",
      "latitude": "46.84802000",
      "longitude": "16.58750000"
   },
   {
      "name": "Zalaszentgrót",
      "countryCode": "HU",
      "stateCode": "ZA",
      "latitude": "46.94474000",
      "longitude": "17.07925000"
   },
   {
      "name": "Zalaszentgróti Járás",
      "countryCode": "HU",
      "stateCode": "ZA",
      "latitude": "46.92070000",
      "longitude": "17.10095000"
   }
]