[
   {
      "name": "Banino",
      "countryCode": "PL",
      "stateCode": "PM",
      "latitude": "54.39215000",
      "longitude": "18.40622000"
   },
   {
      "name": "Bobowo",
      "countryCode": "PL",
      "stateCode": "PM",
      "latitude": "53.88378000",
      "longitude": "18.55681000"
   },
   {
      "name": "Bojano",
      "countryCode": "PL",
      "stateCode": "PM",
      "latitude": "54.47123000",
      "longitude": "18.38408000"
   },
   {
      "name": "Bolszewo",
      "countryCode": "PL",
      "stateCode": "PM",
      "latitude": "54.61801000",
      "longitude": "18.17585000"
   },
   {
      "name": "Borzytuchom",
      "countryCode": "PL",
      "stateCode": "PM",
      "latitude": "54.20021000",
      "longitude": "17.36801000"
   },
   {
      "name": "Brusy",
      "countryCode": "PL",
      "stateCode": "PM",
      "latitude": "53.88446000",
      "longitude": "17.71786000"
   },
   {
      "name": "Bytów",
      "countryCode": "PL",
      "stateCode": "PM",
      "latitude": "54.17057000",
      "longitude": "17.49187000"
   },
   {
      "name": "Cedry Wielkie",
      "countryCode": "PL",
      "stateCode": "PM",
      "latitude": "54.24707000",
      "longitude": "18.84567000"
   },
   {
      "name": "Cewice",
      "countryCode": "PL",
      "stateCode": "PM",
      "latitude": "54.43551000",
      "longitude": "17.73485000"
   },
   {
      "name": "Chmielno",
      "countryCode": "PL",
      "stateCode": "PM",
      "latitude": "54.32543000",
      "longitude": "18.09860000"
   },
   {
      "name": "Choczewo",
      "countryCode": "PL",
      "stateCode": "PM",
      "latitude": "54.73993000",
      "longitude": "17.89175000"
   },
   {
      "name": "Chojnice",
      "countryCode": "PL",
      "stateCode": "PM",
      "latitude": "53.69554000",
      "longitude": "17.55701000"
   },
   {
      "name": "Chwaszczyno",
      "countryCode": "PL",
      "stateCode": "PM",
      "latitude": "54.44379000",
      "longitude": "18.41875000"
   },
   {
      "name": "Chłapowo",
      "countryCode": "PL",
      "stateCode": "PM",
      "latitude": "54.80365000",
      "longitude": "18.37352000"
   },
   {
      "name": "Czarna Dąbrówka",
      "countryCode": "PL",
      "stateCode": "PM",
      "latitude": "54.35631000",
      "longitude": "17.56456000"
   },
   {
      "name": "Czarna Woda",
      "countryCode": "PL",
      "stateCode": "PM",
      "latitude": "53.84458000",
      "longitude": "18.10006000"
   },
   {
      "name": "Czarne",
      "countryCode": "PL",
      "stateCode": "PM",
      "latitude": "53.68420000",
      "longitude": "16.93834000"
   },
   {
      "name": "Czersk",
      "countryCode": "PL",
      "stateCode": "PM",
      "latitude": "53.79589000",
      "longitude": "17.97647000"
   },
   {
      "name": "Człuchów",
      "countryCode": "PL",
      "stateCode": "PM",
      "latitude": "53.66722000",
      "longitude": "17.35883000"
   },
   {
      "name": "Damnica",
      "countryCode": "PL",
      "stateCode": "PM",
      "latitude": "54.50025000",
      "longitude": "17.27154000"
   },
   {
      "name": "Debrzno",
      "countryCode": "PL",
      "stateCode": "PM",
      "latitude": "53.53817000",
      "longitude": "17.23643000"
   },
   {
      "name": "Dziemiany",
      "countryCode": "PL",
      "stateCode": "PM",
      "latitude": "54.00636000",
      "longitude": "17.76755000"
   },
   {
      "name": "Dzierzgoń",
      "countryCode": "PL",
      "stateCode": "PM",
      "latitude": "53.92196000",
      "longitude": "19.34705000"
   },
   {
      "name": "Dębnica Kaszubska",
      "countryCode": "PL",
      "stateCode": "PM",
      "latitude": "54.37831000",
      "longitude": "17.16116000"
   },
   {
      "name": "Garcz",
      "countryCode": "PL",
      "stateCode": "PM",
      "latitude": "54.34760000",
      "longitude": "18.10169000"
   },
   {
      "name": "Gardeja",
      "countryCode": "PL",
      "stateCode": "PM",
      "latitude": "53.61125000",
      "longitude": "18.94687000"
   },
   {
      "name": "Gdańsk",
      "countryCode": "PL",
      "stateCode": "PM",
      "latitude": "54.35205000",
      "longitude": "18.64637000"
   },
   {
      "name": "Gdynia",
      "countryCode": "PL",
      "stateCode": "PM",
      "latitude": "54.51889000",
      "longitude": "18.53188000"
   },
   {
      "name": "Gniew",
      "countryCode": "PL",
      "stateCode": "PM",
      "latitude": "53.83602000",
      "longitude": "18.82310000"
   },
   {
      "name": "Gniewino",
      "countryCode": "PL",
      "stateCode": "PM",
      "latitude": "54.71709000",
      "longitude": "18.01663000"
   },
   {
      "name": "Gnieżdżewo",
      "countryCode": "PL",
      "stateCode": "PM",
      "latitude": "54.74741000",
      "longitude": "18.37944000"
   },
   {
      "name": "Gościcino",
      "countryCode": "PL",
      "stateCode": "PM",
      "latitude": "54.60459000",
      "longitude": "18.15491000"
   },
   {
      "name": "Grabowo Kościerskie",
      "countryCode": "PL",
      "stateCode": "PM",
      "latitude": "54.16816000",
      "longitude": "18.14692000"
   },
   {
      "name": "Główczyce",
      "countryCode": "PL",
      "stateCode": "PM",
      "latitude": "54.61935000",
      "longitude": "17.37230000"
   },
   {
      "name": "Hel",
      "countryCode": "PL",
      "stateCode": "PM",
      "latitude": "54.60814000",
      "longitude": "18.80130000"
   },
   {
      "name": "Jastarnia",
      "countryCode": "PL",
      "stateCode": "PM",
      "latitude": "54.69830000",
      "longitude": "18.67730000"
   },
   {
      "name": "Jastrzębia Góra",
      "countryCode": "PL",
      "stateCode": "PM",
      "latitude": "54.83135000",
      "longitude": "18.31301000"
   },
   {
      "name": "Kaliska",
      "countryCode": "PL",
      "stateCode": "PM",
      "latitude": "53.90535000",
      "longitude": "18.21885000"
   },
   {
      "name": "Karsin",
      "countryCode": "PL",
      "stateCode": "PM",
      "latitude": "53.90768000",
      "longitude": "17.92093000"
   },
   {
      "name": "Kartuzy",
      "countryCode": "PL",
      "stateCode": "PM",
      "latitude": "54.33424000",
      "longitude": "18.19735000"
   },
   {
      "name": "Kobylnica",
      "countryCode": "PL",
      "stateCode": "PM",
      "latitude": "54.43975000",
      "longitude": "16.99782000"
   },
   {
      "name": "Koczała",
      "countryCode": "PL",
      "stateCode": "PM",
      "latitude": "53.90449000",
      "longitude": "17.06529000"
   },
   {
      "name": "Kolbudy",
      "countryCode": "PL",
      "stateCode": "PM",
      "latitude": "54.26989000",
      "longitude": "18.46639000"
   },
   {
      "name": "Koleczkowo",
      "countryCode": "PL",
      "stateCode": "PM",
      "latitude": "54.48629000",
      "longitude": "18.34373000"
   },
   {
      "name": "Kosakowo",
      "countryCode": "PL",
      "stateCode": "PM",
      "latitude": "54.58927000",
      "longitude": "18.48484000"
   },
   {
      "name": "Kowale",
      "countryCode": "PL",
      "stateCode": "PM",
      "latitude": "54.30976000",
      "longitude": "18.56149000"
   },
   {
      "name": "Kołczygłowy",
      "countryCode": "PL",
      "stateCode": "PM",
      "latitude": "54.23895000",
      "longitude": "17.23154000"
   },
   {
      "name": "Kościerzyna",
      "countryCode": "PL",
      "stateCode": "PM",
      "latitude": "54.12226000",
      "longitude": "17.98119000"
   },
   {
      "name": "Krokowa",
      "countryCode": "PL",
      "stateCode": "PM",
      "latitude": "54.77921000",
      "longitude": "18.16160000"
   },
   {
      "name": "Krynica Morska",
      "countryCode": "PL",
      "stateCode": "PM",
      "latitude": "54.38051000",
      "longitude": "19.44413000"
   },
   {
      "name": "Kwidzyn",
      "countryCode": "PL",
      "stateCode": "PM",
      "latitude": "53.72495000",
      "longitude": "18.93114000"
   },
   {
      "name": "Kępice",
      "countryCode": "PL",
      "stateCode": "PM",
      "latitude": "54.24111000",
      "longitude": "16.88968000"
   },
   {
      "name": "Linia",
      "countryCode": "PL",
      "stateCode": "PM",
      "latitude": "54.45143000",
      "longitude": "17.93454000"
   },
   {
      "name": "Liniewo",
      "countryCode": "PL",
      "stateCode": "PM",
      "latitude": "54.07661000",
      "longitude": "18.22675000"
   },
   {
      "name": "Lipnica",
      "countryCode": "PL",
      "stateCode": "PM",
      "latitude": "53.99623000",
      "longitude": "17.40702000"
   },
   {
      "name": "Lipusz",
      "countryCode": "PL",
      "stateCode": "PM",
      "latitude": "54.09806000",
      "longitude": "17.78455000"
   },
   {
      "name": "Lisewo Malborskie",
      "countryCode": "PL",
      "stateCode": "PM",
      "latitude": "54.09665000",
      "longitude": "18.82928000"
   },
   {
      "name": "Lubichowo",
      "countryCode": "PL",
      "stateCode": "PM",
      "latitude": "53.85136000",
      "longitude": "18.39901000"
   },
   {
      "name": "Lublewo Gdańskie",
      "countryCode": "PL",
      "stateCode": "PM",
      "latitude": "54.28457000",
      "longitude": "18.50389000"
   },
   {
      "name": "Luzino",
      "countryCode": "PL",
      "stateCode": "PM",
      "latitude": "54.56604000",
      "longitude": "18.10907000"
   },
   {
      "name": "Lębork",
      "countryCode": "PL",
      "stateCode": "PM",
      "latitude": "54.53921000",
      "longitude": "17.75012000"
   },
   {
      "name": "Malbork",
      "countryCode": "PL",
      "stateCode": "PM",
      "latitude": "54.03591000",
      "longitude": "19.02660000"
   },
   {
      "name": "Miastko",
      "countryCode": "PL",
      "stateCode": "PM",
      "latitude": "54.00283000",
      "longitude": "16.98263000"
   },
   {
      "name": "Mikołajki Pomorskie",
      "countryCode": "PL",
      "stateCode": "PM",
      "latitude": "53.85131000",
      "longitude": "19.16574000"
   },
   {
      "name": "Miłoradz",
      "countryCode": "PL",
      "stateCode": "PM",
      "latitude": "54.01392000",
      "longitude": "18.91846000"
   },
   {
      "name": "Mosty",
      "countryCode": "PL",
      "stateCode": "PM",
      "latitude": "54.61195000",
      "longitude": "18.49634000"
   },
   {
      "name": "Mrzezino",
      "countryCode": "PL",
      "stateCode": "PM",
      "latitude": "54.65378000",
      "longitude": "18.43025000"
   },
   {
      "name": "Nowa Wieś Lęborska",
      "countryCode": "PL",
      "stateCode": "PM",
      "latitude": "54.55878000",
      "longitude": "17.72756000"
   },
   {
      "name": "Nowy Dwór Gdański",
      "countryCode": "PL",
      "stateCode": "PM",
      "latitude": "54.21305000",
      "longitude": "19.11771000"
   },
   {
      "name": "Nowy Staw",
      "countryCode": "PL",
      "stateCode": "PM",
      "latitude": "54.13609000",
      "longitude": "19.00909000"
   },
   {
      "name": "Orle",
      "countryCode": "PL",
      "stateCode": "PM",
      "latitude": "54.64022000",
      "longitude": "18.17057000"
   },
   {
      "name": "Osiek",
      "countryCode": "PL",
      "stateCode": "PM",
      "latitude": "53.72226000",
      "longitude": "18.49051000"
   },
   {
      "name": "Ostaszewo",
      "countryCode": "PL",
      "stateCode": "PM",
      "latitude": "54.21256000",
      "longitude": "18.95142000"
   },
   {
      "name": "Parchowo",
      "countryCode": "PL",
      "stateCode": "PM",
      "latitude": "54.20658000",
      "longitude": "17.66816000"
   },
   {
      "name": "Pelplin",
      "countryCode": "PL",
      "stateCode": "PM",
      "latitude": "53.92834000",
      "longitude": "18.69770000"
   },
   {
      "name": "Pogórze",
      "countryCode": "PL",
      "stateCode": "PM",
      "latitude": "54.56440000",
      "longitude": "18.48209000"
   },
   {
      "name": "Potęgowo",
      "countryCode": "PL",
      "stateCode": "PM",
      "latitude": "54.48285000",
      "longitude": "17.48620000"
   },
   {
      "name": "Powiat bytowski",
      "countryCode": "PL",
      "stateCode": "PM",
      "latitude": "54.15691000",
      "longitude": "17.29147000"
   },
   {
      "name": "Powiat chojnicki",
      "countryCode": "PL",
      "stateCode": "PM",
      "latitude": "53.80099000",
      "longitude": "17.71882000"
   },
   {
      "name": "Powiat człuchowski",
      "countryCode": "PL",
      "stateCode": "PM",
      "latitude": "53.75112000",
      "longitude": "17.18936000"
   },
   {
      "name": "Powiat gdański",
      "countryCode": "PL",
      "stateCode": "PM",
      "latitude": "54.22493000",
      "longitude": "18.58157000"
   },
   {
      "name": "Powiat kartuski",
      "countryCode": "PL",
      "stateCode": "PM",
      "latitude": "54.32687000",
      "longitude": "18.08632000"
   },
   {
      "name": "Powiat kościerski",
      "countryCode": "PL",
      "stateCode": "PM",
      "latitude": "54.01939000",
      "longitude": "18.00400000"
   },
   {
      "name": "Powiat kwidzyński",
      "countryCode": "PL",
      "stateCode": "PM",
      "latitude": "53.74690000",
      "longitude": "19.03111000"
   },
   {
      "name": "Powiat lęborski",
      "countryCode": "PL",
      "stateCode": "PM",
      "latitude": "54.56830000",
      "longitude": "17.65178000"
   },
   {
      "name": "Powiat malborski",
      "countryCode": "PL",
      "stateCode": "PM",
      "latitude": "54.06329000",
      "longitude": "19.04421000"
   },
   {
      "name": "Powiat nowodworski",
      "countryCode": "PL",
      "stateCode": "PM",
      "latitude": "54.28730000",
      "longitude": "19.24266000"
   },
   {
      "name": "Powiat pucki",
      "countryCode": "PL",
      "stateCode": "PM",
      "latitude": "54.69659000",
      "longitude": "18.36979000"
   },
   {
      "name": "Powiat starogardzki",
      "countryCode": "PL",
      "stateCode": "PM",
      "latitude": "53.89912000",
      "longitude": "18.39912000"
   },
   {
      "name": "Powiat sztumski",
      "countryCode": "PL",
      "stateCode": "PM",
      "latitude": "53.90149000",
      "longitude": "19.22000000"
   },
   {
      "name": "Powiat słupski",
      "countryCode": "PL",
      "stateCode": "PM",
      "latitude": "54.42211000",
      "longitude": "17.15917000"
   },
   {
      "name": "Powiat tczewski",
      "countryCode": "PL",
      "stateCode": "PM",
      "latitude": "53.91895000",
      "longitude": "18.71916000"
   },
   {
      "name": "Powiat wejherowski",
      "countryCode": "PL",
      "stateCode": "PM",
      "latitude": "54.61707000",
      "longitude": "18.04881000"
   },
   {
      "name": "Prabuty",
      "countryCode": "PL",
      "stateCode": "PM",
      "latitude": "53.75500000",
      "longitude": "19.20547000"
   },
   {
      "name": "Pruszcz Gdański",
      "countryCode": "PL",
      "stateCode": "PM",
      "latitude": "54.26217000",
      "longitude": "18.63625000"
   },
   {
      "name": "Przechlewo",
      "countryCode": "PL",
      "stateCode": "PM",
      "latitude": "53.79847000",
      "longitude": "17.25205000"
   },
   {
      "name": "Przodkowo",
      "countryCode": "PL",
      "stateCode": "PM",
      "latitude": "54.37991000",
      "longitude": "18.28760000"
   },
   {
      "name": "Przywidz",
      "countryCode": "PL",
      "stateCode": "PM",
      "latitude": "54.19524000",
      "longitude": "18.32116000"
   },
   {
      "name": "Pszczółki",
      "countryCode": "PL",
      "stateCode": "PM",
      "latitude": "54.17304000",
      "longitude": "18.69787000"
   },
   {
      "name": "Puck",
      "countryCode": "PL",
      "stateCode": "PM",
      "latitude": "54.71790000",
      "longitude": "18.40841000"
   },
   {
      "name": "Reda",
      "countryCode": "PL",
      "stateCode": "PM",
      "latitude": "54.60528000",
      "longitude": "18.34717000"
   },
   {
      "name": "Rekowo Dolne",
      "countryCode": "PL",
      "stateCode": "PM",
      "latitude": "54.63133000",
      "longitude": "18.36279000"
   },
   {
      "name": "Rotmanka",
      "countryCode": "PL",
      "stateCode": "PM",
      "latitude": "54.27425000",
      "longitude": "18.60380000"
   },
   {
      "name": "Rumia",
      "countryCode": "PL",
      "stateCode": "PM",
      "latitude": "54.57092000",
      "longitude": "18.38802000"
   },
   {
      "name": "Ryjewo",
      "countryCode": "PL",
      "stateCode": "PM",
      "latitude": "53.84463000",
      "longitude": "18.96077000"
   },
   {
      "name": "Rzeczenica",
      "countryCode": "PL",
      "stateCode": "PM",
      "latitude": "53.75790000",
      "longitude": "17.10752000"
   },
   {
      "name": "Sadlinki",
      "countryCode": "PL",
      "stateCode": "PM",
      "latitude": "53.66539000",
      "longitude": "18.86807000"
   },
   {
      "name": "Sierakowice",
      "countryCode": "PL",
      "stateCode": "PM",
      "latitude": "54.34610000",
      "longitude": "17.89252000"
   },
   {
      "name": "Skarszewy",
      "countryCode": "PL",
      "stateCode": "PM",
      "latitude": "54.06911000",
      "longitude": "18.44416000"
   },
   {
      "name": "Skórcz",
      "countryCode": "PL",
      "stateCode": "PM",
      "latitude": "53.79436000",
      "longitude": "18.52561000"
   },
   {
      "name": "Smołdzino",
      "countryCode": "PL",
      "stateCode": "PM",
      "latitude": "54.66318000",
      "longitude": "17.21369000"
   },
   {
      "name": "Smętowo Graniczne",
      "countryCode": "PL",
      "stateCode": "PM",
      "latitude": "53.74638000",
      "longitude": "18.68586000"
   },
   {
      "name": "Somonino",
      "countryCode": "PL",
      "stateCode": "PM",
      "latitude": "54.27555000",
      "longitude": "18.19885000"
   },
   {
      "name": "Sopot",
      "countryCode": "PL",
      "stateCode": "PM",
      "latitude": "54.44180000",
      "longitude": "18.56003000"
   },
   {
      "name": "Stara Kiszewa",
      "countryCode": "PL",
      "stateCode": "PM",
      "latitude": "53.99006000",
      "longitude": "18.16958000"
   },
   {
      "name": "Stare Pole",
      "countryCode": "PL",
      "stateCode": "PM",
      "latitude": "54.05667000",
      "longitude": "19.20874000"
   },
   {
      "name": "Starogard Gdański",
      "countryCode": "PL",
      "stateCode": "PM",
      "latitude": "53.96396000",
      "longitude": "18.52638000"
   },
   {
      "name": "Stary Targ",
      "countryCode": "PL",
      "stateCode": "PM",
      "latitude": "53.92335000",
      "longitude": "19.17003000"
   },
   {
      "name": "Stegna",
      "countryCode": "PL",
      "stateCode": "PM",
      "latitude": "54.32684000",
      "longitude": "19.11252000"
   },
   {
      "name": "Straszyn",
      "countryCode": "PL",
      "stateCode": "PM",
      "latitude": "54.27214000",
      "longitude": "18.58114000"
   },
   {
      "name": "Strzelno",
      "countryCode": "PL",
      "stateCode": "PM",
      "latitude": "54.78564000",
      "longitude": "18.32515000"
   },
   {
      "name": "Studzienice",
      "countryCode": "PL",
      "stateCode": "PM",
      "latitude": "54.09262000",
      "longitude": "17.57581000"
   },
   {
      "name": "Stężyca",
      "countryCode": "PL",
      "stateCode": "PM",
      "latitude": "54.20593000",
      "longitude": "17.95569000"
   },
   {
      "name": "Subkowy",
      "countryCode": "PL",
      "stateCode": "PM",
      "latitude": "54.00227000",
      "longitude": "18.76928000"
   },
   {
      "name": "Suchy Dąb",
      "countryCode": "PL",
      "stateCode": "PM",
      "latitude": "54.20809000",
      "longitude": "18.76731000"
   },
   {
      "name": "Sulęczyno",
      "countryCode": "PL",
      "stateCode": "PM",
      "latitude": "54.23302000",
      "longitude": "17.77330000"
   },
   {
      "name": "Szemud",
      "countryCode": "PL",
      "stateCode": "PM",
      "latitude": "54.48709000",
      "longitude": "18.22280000"
   },
   {
      "name": "Szlachta",
      "countryCode": "PL",
      "stateCode": "PM",
      "latitude": "53.76827000",
      "longitude": "18.11367000"
   },
   {
      "name": "Sztum",
      "countryCode": "PL",
      "stateCode": "PM",
      "latitude": "53.92077000",
      "longitude": "19.03072000"
   },
   {
      "name": "Sztutowo",
      "countryCode": "PL",
      "stateCode": "PM",
      "latitude": "54.32679000",
      "longitude": "19.17921000"
   },
   {
      "name": "Słupsk",
      "countryCode": "PL",
      "stateCode": "PM",
      "latitude": "54.46405000",
      "longitude": "17.02872000"
   },
   {
      "name": "Tczew",
      "countryCode": "PL",
      "stateCode": "PM",
      "latitude": "54.09242000",
      "longitude": "18.77787000"
   },
   {
      "name": "Trzebielino",
      "countryCode": "PL",
      "stateCode": "PM",
      "latitude": "54.19996000",
      "longitude": "17.08726000"
   },
   {
      "name": "Trąbki Wielkie",
      "countryCode": "PL",
      "stateCode": "PM",
      "latitude": "54.17062000",
      "longitude": "18.54003000"
   },
   {
      "name": "Tuchomie",
      "countryCode": "PL",
      "stateCode": "PM",
      "latitude": "54.11522000",
      "longitude": "17.33634000"
   },
   {
      "name": "Ustka",
      "countryCode": "PL",
      "stateCode": "PM",
      "latitude": "54.58048000",
      "longitude": "16.86194000"
   },
   {
      "name": "Wejherowo",
      "countryCode": "PL",
      "stateCode": "PM",
      "latitude": "54.60568000",
      "longitude": "18.23559000"
   },
   {
      "name": "Wielki Kack",
      "countryCode": "PL",
      "stateCode": "PM",
      "latitude": "54.46754000",
      "longitude": "18.48810000"
   },
   {
      "name": "Wierzchucino",
      "countryCode": "PL",
      "stateCode": "PM",
      "latitude": "54.78797000",
      "longitude": "18.00307000"
   },
   {
      "name": "Władysławowo",
      "countryCode": "PL",
      "stateCode": "PM",
      "latitude": "54.79086000",
      "longitude": "18.40090000"
   },
   {
      "name": "Zblewo",
      "countryCode": "PL",
      "stateCode": "PM",
      "latitude": "53.93366000",
      "longitude": "18.32262000"
   },
   {
      "name": "Łeba",
      "countryCode": "PL",
      "stateCode": "PM",
      "latitude": "54.76099000",
      "longitude": "17.55547000"
   },
   {
      "name": "Łęczyce",
      "countryCode": "PL",
      "stateCode": "PM",
      "latitude": "54.59405000",
      "longitude": "17.85931000"
   },
   {
      "name": "Łęgowo",
      "countryCode": "PL",
      "stateCode": "PM",
      "latitude": "54.22641000",
      "longitude": "18.64277000"
   },
   {
      "name": "Żelistrzewo",
      "countryCode": "PL",
      "stateCode": "PM",
      "latitude": "54.67770000",
      "longitude": "18.41738000"
   },
   {
      "name": "Żukowo",
      "countryCode": "PL",
      "stateCode": "PM",
      "latitude": "54.34220000",
      "longitude": "18.36476000"
   }
]