[
   {
      "name": "Dasht-e Archī",
      "countryCode": "AF",
      "stateCode": "KDZ",
      "latitude": "37.13333000",
      "longitude": "69.16667000"
   },
   {
      "name": "Imām Şāḩib",
      "countryCode": "AF",
      "stateCode": "KDZ",
      "latitude": "37.18897000",
      "longitude": "68.93644000"
   },
   {
      "name": "Khanabad",
      "countryCode": "AF",
      "stateCode": "KDZ",
      "latitude": "36.68250000",
      "longitude": "69.11556000"
   },
   {
      "name": "Kunduz",
      "countryCode": "AF",
      "stateCode": "KDZ",
      "latitude": "36.72895000",
      "longitude": "68.85700000"
   },
   {
      "name": "Qarāwul",
      "countryCode": "AF",
      "stateCode": "KDZ",
      "latitude": "37.21959000",
      "longitude": "68.78020000"
   }
]